{
  "navigation": [
    {
      "id": 1,
      "title": "Главная",
      "path": "/"
    },
    {
      "id": 2,
      "title": "О нас",
      "path": "/about"
    },
    {
      "id": 3,
      "title": "Каталог",
      "path": "/catalog"
    },
    {
      "id": 4,
      "title": "Контакты",
      "path": "/contacts"
    }
  ],
  "categories": [
    {
      "id": 1,
      "title": "Рубашка"
    },
    {
      "id": 2,
      "title": "Обувь"
    },
    {
      "id": 3,
      "title": "Бомберы"
    },
    {
      "id": 4,
      "title": "Брюки"
    },
    {
      "id": 5,
      "title": "Платье"
    },
    {
      "id": 6,
      "title": "Пиджак"
    }
  ],
  "trends": [
    {
      "id": 1,
      "image": "trend-1.webp",
      "title": "РАСПОЛОСОВАЛИ",
      "description": "Еще по результатам первой в сезоне недели моды — Нью-Йоркской — стало ясно, что полоска сместит цветы с пьедестала главного принта сезона. Толстая или тонкая, горизонтальная или вертикальная, черно-белая или цветная — в моде все виды полосок."
    },
    {
      "id": 2,
      "image": "trend-2.webp",
      "title": "КОСАЯ САЖЕНЬ",
      "description": "Самые модные платья и юбки весны — асимметрично скроенные, не важно, костюмные они, как у Alexander McQueen, или летящие шелковые, как у Dries Van Noten, Victoria Beckham и 3.1 Phillip Lim. Стилисты любят говорить, что диагональные линии добавляют образу «динамичности»: чтобы это ни значило, тренд мы одобряем."
    },
    {
      "id": 3,
      "image": "trend-3.webp",
      "title": "ФИСТАШКОВОЕ МОРОЖЕНОЕ",
      "description": "Главный десерт в буфете образца весна—лето 2025."
    },
    {
      "id": 5,
      "image": "trend-5.webp",
      "title": "ВСЕ ПЕРЕПЛЕТЕНО",
      "description": "Ажурные платья и юбки, топы и даже колготки звезды стритстайла и соцсетей с блеском освоили еще весной и летом 2024 года. Хорошие новости — все эти вещи пригодятся им в новом весенне-летнем сезоне: внимание дизайнеров к романтичному тренду стало еще пристальнее. К тому же теперь бренды определились со своим фаворитом — это кружево белого цвета. Тонкое, как паутинка, или, напротив, крупное и объемное кроше."
    },
    {
      "id": 6,
      "image": "trend-6.webp",
      "title": "ГОЛУБИКА В ШОКОЛАДЕ",
      "description": "«По коллекциям недель моды сезона весна—лето 2025 можно изучить все оттенки коричневого», — писали мы, предлагая соответствующий шопинг-гид. Теперь возвращаемся с уточнением: эффектнее всего коричневые вещи смотрятся в тандеме с голубыми."
    }
  ],
  "catalog": [
    {
      "id": 1,
      "title": "Рубашка CANDY",
      "image": ["catalog-1-1.webp", "catalog-1-2.jpg", "catalog-1-3.jpg"],
      "price": 13600,
      "oldPrice": 0,
      "info": "Рубашка «CANDY» из нежного хлопка с акцентным вырезом на спине. Состав:100% хлопок",
      "categoryId": 1,
      "trendId": 1,
      "new": false,
      "popular": true,
      "measurements": "<p>XS (40-42)| 78-86 (Грудь)| 58-66 см (Талия)| 86-94 см (Бёдра)<br><u>S (42-44)</u>| 82-90 (Грудь)&nbsp;| 62-70 см (Талия)| 90-98 см&nbsp;(Бёдра)<br><u>M (44-46)</u>|&nbsp;86-94 (Грудь)&nbsp;|66-74 см (Талия)| 94-102 см&nbsp;(Бёдра)<br><u>L&nbsp;(46-48)</u>| 90-98 (Грудь)&nbsp;| 70-78 см (Талия)| 98-104 см&nbsp;(Бёдра)<br><u>XL&nbsp;(48-50)</u>| 94-102 (Грудь)&nbsp;| 74-82 см (Талия)| 102-110 см&nbsp;(Бёдра)<br><u>ONESIZE (42-48)</u>&nbsp;| 78-98 (Грудь)&nbsp;| 62-78 см (Талия)| 82-104см&nbsp;(Бёдра)</p>",
      "care": "<p>Хлопковые ткани можно загружать в стиральную машину. Если ткань слишком тонка или вы дорожите ее цветом &ndash; лучше всего отстирать руками.<br><u>Как меня стирать</u></p><ul><li>Одежду нужно вывернуть наизнанку, это позволит сберечь внешний вид наружной стороны ткани;</li><li>Пуговицы и молнии застегнуть;</li><li>При стирке хлопчатой одежды необходимо соблюдать температурный режим и стирать при 30-40&deg;C;</li><li>Вещи из хлопка рекомендуется стирать отдельно от другой одежды, потому что этот материал во время стирки может растягиваться;</li><li>Если на изделии есть пятна, их лучше заранее вывести специальным средством</li></ul><p><u>Как меня сушить</u></p><ul><li>Вещи лучше не отжимать или делать это максимально щадяще;</li><li>Вывешивайте одежду сразу после стирки, это позволит придать вещам максимальную формостойкость и избежать помятостей;</li><li>Сушить лучше всего только в тех местах, где исключено прямое попадание солнечных лучей на одежду.</li></ul><p><u>Как меня гладить</u></p><ul><li>Гладить одежду нужно с изнаночной стороны;</li><li>Перед глажкой тонкого изделия лучше проверить устойчивость к высоким температурам на незаметном участке;</li><li>Главное &ndash; не пересушить хлопок. Если не удалось избежать этого неприятного явления, то перед тем как гладить, можно сбрызнуть слегка водой;</li><li>Чтобы предотвратить растягивание, водить утюгом нужно вдоль.</li></ul>"
    },
    {
      "id": 2,
      "title": "Рубашка POLOSKA",
      "image": ["catalog-2-1.webp", "catalog-2-2.webp", "catalog-2-3.jpg"],
      "price": 8900,
      "oldPrice": 0,
      "info": "Цвета: голубой Размерный ряд: one size Состав: хлопок 100% Рубашка кроп из вываренного 100% хлопка. Пуговицы в коричневом оттенке под кость и брендированная кожаная нашивка дополняют акцент на базовой рубашке. В комплекте тонкий пояс-шнурок.",
      "categoryId": 1,
      "trendId": 1,
      "new": true,
      "popular": false,
      "measurements": "<p>XS (40-42)| 78-86 (Грудь)| 58-66 см (Талия)| 86-94 см (Бёдра)<br><u>S (42-44)</u>| 82-90 (Грудь)&nbsp;| 62-70 см (Талия)| 90-98 см&nbsp;(Бёдра)<br><u>M (44-46)</u>|&nbsp;86-94 (Грудь)&nbsp;|66-74 см (Талия)| 94-102 см&nbsp;(Бёдра)<br><u>L&nbsp;(46-48)</u>| 90-98 (Грудь)&nbsp;| 70-78 см (Талия)| 98-104 см&nbsp;(Бёдра)<br><u>XL&nbsp;(48-50)</u>| 94-102 (Грудь)&nbsp;| 74-82 см (Талия)| 102-110 см&nbsp;(Бёдра)<br><u>ONESIZE (42-48)</u>&nbsp;| 78-98 (Грудь)&nbsp;| 62-78 см (Талия)| 82-104см&nbsp;(Бёдра)</p>",
      "care": "<p>Хлопковые ткани можно загружать в стиральную машину. Если ткань слишком тонка или вы дорожите ее цветом &ndash; лучше всего отстирать руками.<br><u>Как меня стирать</u></p><ul><li>Одежду нужно вывернуть наизнанку, это позволит сберечь внешний вид наружной стороны ткани;</li><li>Пуговицы и молнии застегнуть;</li><li>При стирке хлопчатой одежды необходимо соблюдать температурный режим и стирать при 30-40&deg;C;</li><li>Вещи из хлопка рекомендуется стирать отдельно от другой одежды, потому что этот материал во время стирки может растягиваться;</li><li>Если на изделии есть пятна, их лучше заранее вывести специальным средством</li></ul><p><u>Как меня сушить</u></p><ul><li>Вещи лучше не отжимать или делать это максимально щадяще;</li><li>Вывешивайте одежду сразу после стирки, это позволит придать вещам максимальную формостойкость и избежать помятостей;</li><li>Сушить лучше всего только в тех местах, где исключено прямое попадание солнечных лучей на одежду.</li></ul><p><u>Как меня гладить</u></p><ul><li>Гладить одежду нужно с изнаночной стороны;</li><li>Перед глажкой тонкого изделия лучше проверить устойчивость к высоким температурам на незаметном участке;</li><li>Главное &ndash; не пересушить хлопок. Если не удалось избежать этого неприятного явления, то перед тем как гладить, можно сбрызнуть слегка водой;</li><li>Чтобы предотвратить растягивание, водить утюгом нужно вдоль.</li></ul>"
    },
    {
      "id": 3,
      "title": "Рубашка пижамная",
      "image": ["catalog-3-1.webp", "catalog-3-2.webp", "catalog-3-3.jpg"],
      "price": 10000,
      "oldPrice": 0,
      "info": "Состав:100% хлопок",
      "categoryId": 1,
      "trendId": 1,
      "new": false,
      "popular": false,
      "measurements": "<p>XS (40-42)| 78-86 (Грудь)| 58-66 см (Талия)| 86-94 см (Бёдра)<br><u>S (42-44)</u>| 82-90 (Грудь)&nbsp;| 62-70 см (Талия)| 90-98 см&nbsp;(Бёдра)<br><u>M (44-46)</u>|&nbsp;86-94 (Грудь)&nbsp;|66-74 см (Талия)| 94-102 см&nbsp;(Бёдра)<br><u>L&nbsp;(46-48)</u>| 90-98 (Грудь)&nbsp;| 70-78 см (Талия)| 98-104 см&nbsp;(Бёдра)<br><u>XL&nbsp;(48-50)</u>| 94-102 (Грудь)&nbsp;| 74-82 см (Талия)| 102-110 см&nbsp;(Бёдра)<br><u>ONESIZE (42-48)</u>&nbsp;| 78-98 (Грудь)&nbsp;| 62-78 см (Талия)| 82-104см&nbsp;(Бёдра)</p>",
      "care": "<p>Хлопковые ткани можно загружать в стиральную машину. Если ткань слишком тонка или вы дорожите ее цветом &ndash; лучше всего отстирать руками.<br><u>Как меня стирать</u></p><ul><li>Одежду нужно вывернуть наизнанку, это позволит сберечь внешний вид наружной стороны ткани;</li><li>Пуговицы и молнии застегнуть;</li><li>При стирке хлопчатой одежды необходимо соблюдать температурный режим и стирать при 30-40&deg;C;</li><li>Вещи из хлопка рекомендуется стирать отдельно от другой одежды, потому что этот материал во время стирки может растягиваться;</li><li>Если на изделии есть пятна, их лучше заранее вывести специальным средством</li></ul><p><u>Как меня сушить</u></p><ul><li>Вещи лучше не отжимать или делать это максимально щадяще;</li><li>Вывешивайте одежду сразу после стирки, это позволит придать вещам максимальную формостойкость и избежать помятостей;</li><li>Сушить лучше всего только в тех местах, где исключено прямое попадание солнечных лучей на одежду.</li></ul><p><u>Как меня гладить</u></p><ul><li>Гладить одежду нужно с изнаночной стороны;</li><li>Перед глажкой тонкого изделия лучше проверить устойчивость к высоким температурам на незаметном участке;</li><li>Главное &ndash; не пересушить хлопок. Если не удалось избежать этого неприятного явления, то перед тем как гладить, можно сбрызнуть слегка водой;</li><li>Чтобы предотвратить растягивание, водить утюгом нужно вдоль.</li></ul>"
    },
    {
      "id": 4,
      "title": "Рубашка Вингс",
      "image": ["catalog-4-1.webp", "catalog-4-2.jpg", "catalog-4-3.webp"],
      "price": 14900,
      "oldPrice": 0,
      "info": "Варианты трансформирования «крыльев» позволяют создать множество луков, меняя ваши образы до неузнаваемости. - ⁠Приталенный силуэт. - «Крылья» функциональны и имеют возможность трансформироваться: 1.⁠ ⁠Ну, во-первых, их можно просто использовать как пояс. 2.⁠ ⁠На «крыльях» есть потайная пуговица и петля, которые позволяют сделать из них баску-юбку вторым слоем спереди или сзади изделия 3.⁠ ⁠Также с помощью крыльев-пояса можно сделать имитацию жилетки, завязав хвосты на шее. Изделие отлично вписывается в базовый гардероб. Можно носить как рубашку под брюки или юбку застегнув полностью или же частично до пояса. ⁠Круто будет смотреться с любой обувью: от соломенных мюли до грубых ботинок. Придумывайте свои неповторимые образы. Ярких сезонов и теплых вечеров. Состав: 100% лен (коричневый), 80% вискоза, 20% полиэстер (черный)",
      "categoryId": 1,
      "trendId": 2,
      "new": true,
      "popular": false,
      "measurements": "<p>XS (40-42)| 78-86 (Грудь)| 58-66 см (Талия)| 86-94 см (Бёдра)<br><u>S (42-44)</u>| 82-90 (Грудь)&nbsp;| 62-70 см (Талия)| 90-98 см&nbsp;(Бёдра)<br><u>M (44-46)</u>|&nbsp;86-94 (Грудь)&nbsp;|66-74 см (Талия)| 94-102 см&nbsp;(Бёдра)<br><u>L&nbsp;(46-48)</u>| 90-98 (Грудь)&nbsp;| 70-78 см (Талия)| 98-104 см&nbsp;(Бёдра)<br><u>XL&nbsp;(48-50)</u>| 94-102 (Грудь)&nbsp;| 74-82 см (Талия)| 102-110 см&nbsp;(Бёдра)<br><u>ONESIZE (42-48)</u>&nbsp;| 78-98 (Грудь)&nbsp;| 62-78 см (Талия)| 82-104см&nbsp;(Бёдра)</p>",
      "care": "<p>Хлопковые ткани можно загружать в стиральную машину. Если ткань слишком тонка или вы дорожите ее цветом &ndash; лучше всего отстирать руками.<br><u>Как меня стирать</u></p><ul><li>Одежду нужно вывернуть наизнанку, это позволит сберечь внешний вид наружной стороны ткани;</li><li>Пуговицы и молнии застегнуть;</li><li>При стирке хлопчатой одежды необходимо соблюдать температурный режим и стирать при 30-40&deg;C;</li><li>Вещи из хлопка рекомендуется стирать отдельно от другой одежды, потому что этот материал во время стирки может растягиваться;</li><li>Если на изделии есть пятна, их лучше заранее вывести специальным средством</li></ul><p><u>Как меня сушить</u></p><ul><li>Вещи лучше не отжимать или делать это максимально щадяще;</li><li>Вывешивайте одежду сразу после стирки, это позволит придать вещам максимальную формостойкость и избежать помятостей;</li><li>Сушить лучше всего только в тех местах, где исключено прямое попадание солнечных лучей на одежду.</li></ul><p><u>Как меня гладить</u></p><ul><li>Гладить одежду нужно с изнаночной стороны;</li><li>Перед глажкой тонкого изделия лучше проверить устойчивость к высоким температурам на незаметном участке;</li><li>Главное &ndash; не пересушить хлопок. Если не удалось избежать этого неприятного явления, то перед тем как гладить, можно сбрызнуть слегка водой;</li><li>Чтобы предотвратить растягивание, водить утюгом нужно вдоль.</li></ul>"
    },
    {
      "id": 5,
      "title": "Рубашка-платье макси",
      "image": ["catalog-5-1.webp", "catalog-5-2.jpg", "catalog-5-3.webp"],
      "price": 16700,
      "oldPrice": 0,
      "info": "Платье-рубашка длины макси может быть как отдельной единицей в гардеробе, так и нижнем слоем под платье-жилет из костюмной группы. Широкий манжет, застежка-планка по полочке, один нагрудный карман. Состав: 97% хлопок, 3% эластан",
      "categoryId": 1,
      "trendId": 2,
      "new": false,
      "popular": true,
      "measurements": "<p>XS (40-42)| 78-86 (Грудь)| 58-66 см (Талия)| 86-94 см (Бёдра)<br><u>S (42-44)</u>| 82-90 (Грудь)&nbsp;| 62-70 см (Талия)| 90-98 см&nbsp;(Бёдра)<br><u>M (44-46)</u>|&nbsp;86-94 (Грудь)&nbsp;|66-74 см (Талия)| 94-102 см&nbsp;(Бёдра)<br><u>L&nbsp;(46-48)</u>| 90-98 (Грудь)&nbsp;| 70-78 см (Талия)| 98-104 см&nbsp;(Бёдра)<br><u>XL&nbsp;(48-50)</u>| 94-102 (Грудь)&nbsp;| 74-82 см (Талия)| 102-110 см&nbsp;(Бёдра)<br><u>ONESIZE (42-48)</u>&nbsp;| 78-98 (Грудь)&nbsp;| 62-78 см (Талия)| 82-104см&nbsp;(Бёдра)</p>",
      "care": "<p>Хлопковые ткани можно загружать в стиральную машину. Если ткань слишком тонка или вы дорожите ее цветом &ndash; лучше всего отстирать руками.<br><u>Как меня стирать</u></p><ul><li>Одежду нужно вывернуть наизнанку, это позволит сберечь внешний вид наружной стороны ткани;</li><li>Пуговицы и молнии застегнуть;</li><li>При стирке хлопчатой одежды необходимо соблюдать температурный режим и стирать при 30-40&deg;C;</li><li>Вещи из хлопка рекомендуется стирать отдельно от другой одежды, потому что этот материал во время стирки может растягиваться;</li><li>Если на изделии есть пятна, их лучше заранее вывести специальным средством</li></ul><p><u>Как меня сушить</u></p><ul><li>Вещи лучше не отжимать или делать это максимально щадяще;</li><li>Вывешивайте одежду сразу после стирки, это позволит придать вещам максимальную формостойкость и избежать помятостей;</li><li>Сушить лучше всего только в тех местах, где исключено прямое попадание солнечных лучей на одежду.</li></ul><p><u>Как меня гладить</u></p><ul><li>Гладить одежду нужно с изнаночной стороны;</li><li>Перед глажкой тонкого изделия лучше проверить устойчивость к высоким температурам на незаметном участке;</li><li>Главное &ndash; не пересушить хлопок. Если не удалось избежать этого неприятного явления, то перед тем как гладить, можно сбрызнуть слегка водой;</li><li>Чтобы предотвратить растягивание, водить утюгом нужно вдоль.</li></ul>"
    },
    {
      "id": 6,
      "title": "Рубашка без манжет",
      "image": ["catalog-6-1.webp", "catalog-6-2.jpg", "catalog-6-3.webp"],
      "price": 10000,
      "oldPrice": 0,
      "info": "Состав:100% хлопок",
      "categoryId": 1,
      "trendId": 6,
      "new": false,
      "popular": true,
      "measurements": "<p>XS (40-42)| 78-86 (Грудь)| 58-66 см (Талия)| 86-94 см (Бёдра)<br><u>S (42-44)</u>| 82-90 (Грудь)&nbsp;| 62-70 см (Талия)| 90-98 см&nbsp;(Бёдра)<br><u>M (44-46)</u>|&nbsp;86-94 (Грудь)&nbsp;|66-74 см (Талия)| 94-102 см&nbsp;(Бёдра)<br><u>L&nbsp;(46-48)</u>| 90-98 (Грудь)&nbsp;| 70-78 см (Талия)| 98-104 см&nbsp;(Бёдра)<br><u>XL&nbsp;(48-50)</u>| 94-102 (Грудь)&nbsp;| 74-82 см (Талия)| 102-110 см&nbsp;(Бёдра)<br><u>ONESIZE (42-48)</u>&nbsp;| 78-98 (Грудь)&nbsp;| 62-78 см (Талия)| 82-104см&nbsp;(Бёдра)</p>",
      "care": "<p>Хлопковые ткани можно загружать в стиральную машину. Если ткань слишком тонка или вы дорожите ее цветом &ndash; лучше всего отстирать руками.<br><u>Как меня стирать</u></p><ul><li>Одежду нужно вывернуть наизнанку, это позволит сберечь внешний вид наружной стороны ткани;</li><li>Пуговицы и молнии застегнуть;</li><li>При стирке хлопчатой одежды необходимо соблюдать температурный режим и стирать при 30-40&deg;C;</li><li>Вещи из хлопка рекомендуется стирать отдельно от другой одежды, потому что этот материал во время стирки может растягиваться;</li><li>Если на изделии есть пятна, их лучше заранее вывести специальным средством</li></ul><p><u>Как меня сушить</u></p><ul><li>Вещи лучше не отжимать или делать это максимально щадяще;</li><li>Вывешивайте одежду сразу после стирки, это позволит придать вещам максимальную формостойкость и избежать помятостей;</li><li>Сушить лучше всего только в тех местах, где исключено прямое попадание солнечных лучей на одежду.</li></ul><p><u>Как меня гладить</u></p><ul><li>Гладить одежду нужно с изнаночной стороны;</li><li>Перед глажкой тонкого изделия лучше проверить устойчивость к высоким температурам на незаметном участке;</li><li>Главное &ndash; не пересушить хлопок. Если не удалось избежать этого неприятного явления, то перед тем как гладить, можно сбрызнуть слегка водой;</li><li>Чтобы предотвратить растягивание, водить утюгом нужно вдоль.</li></ul>"
    },
    {
      "id": 7,
      "title": "Балетки 17-587-811D Черный",
      "image": ["catalog-7-1.webp", "catalog-7-2.webp", "catalog-7-3.jpg"],
      "price": 18500,
      "oldPrice": 0,
      "info": "Сезон - мультисезон Материал верха - натуральная кожа Материал подкладки - натуральная кожа Стелька - натуральная кожа Высота каблука - 1 см",
      "categoryId": 2,
      "trendId": 0,
      "new": false,
      "popular": false,
      "measurements": "",
      "care": ""
    },
    {
      "id": 8,
      "title": "Балетки 22A1-08A-1 Черный",
      "image": ["catalog-8-1.webp", "catalog-8-2.jpg", "catalog-8-3.jpg"],
      "price": 19900,
      "oldPrice": 0,
      "info": "Сезон - Мультисезон Материал верха - Натуральный мех Материал подкладки - Натуральная кожа Стелька - Натуральная кожа Высота каблука - 1,5 см",
      "categoryId": 2,
      "trendId": 0,
      "new": false,
      "popular": false,
      "measurements": "",
      "care": ""
    },
    {
      "id": 9,
      "title": "Ботильоны B001 Синий",
      "image": ["catalog-9-1.webp", "catalog-9-2.jpg", "catalog-9-3.jpg"],
      "price": 9800,
      "oldPrice": 0,
      "info": "Сезон - Демисезон Материал верха - Текстиль Материал подкладки - Натуральная кожа Стелька - Натуральная кожа Высота голенища - 19 см Обхват голенища - 32 см Высота каблука - 7 см",
      "categoryId": 2,
      "trendId": 0,
      "new": false,
      "popular": false,
      "measurements": "",
      "care": ""
    },
    {
      "id": 10,
      "title": "Ботильоны G352-656 Черный",
      "image": ["catalog-10-1.webp", "catalog-10-2.jpg", "catalog-10-3.jpg"],
      "price": 31500,
      "oldPrice": 0,
      "info": "Сезон - Демисезон Материал верха - Натуральная кожа Материал подкладки - Натуральная кожа Стелька - Натуральная кожа",
      "categoryId": 2,
      "trendId": 0,
      "new": false,
      "popular": false,
      "measurements": "",
      "care": "<div>Часто можно услышать высказывание, что натуральная кожа износостойкая, долго служит, её внешний вид не портится, и многие года она будет служить верой и правдой. Но чтобы все слова про долговечность и износостойкость подтвердились - натуральной коже необходим правильный уход.<br><u>Как меня стирать</u><br><ul><li>При очистке изделий от небольшого загрязнения можно воспользоваться чистой мягкой тканью;</li><li>Не погружайте изделия из кожи в воду или другие жидкости;</li><li>Не используйте растворители, химические и другие активные вещества;</li><li>Кожаные изделия можно почистить раствором, состоящим из воды, мыла и нашатырного спирта, а затем для блеска слегка потереть тряпочкой, смоченной касторовым маслом.</li></ul><u>Как меня сушить</u><br><ul><li>При намокании дайте изделию высохнуть естественным путем при комнатной температуре. Не используйте искусственное тепло для ускорения процесса сушки;</li><li>Не сушите горячим воздухом или под воздействием солнечных лучей.</li></ul><u>Как меня гладить</u><br><ul><li>Не храните кожаные изделия в пластиковых мешках и не держите их на ярком солнце, это может привести к изменению цвета кожи или выцветанию;</li><li>Так как кожа дышит, она требует, соответственно, и упаковки, которая дышит. Самый лучший вариант - тканевые мешки и картонные коробки;</li><li>К нашим сумкам прилагается специальный мешочек (пыльник) из нетканного материала (он имеет мягкую неворсистую поверхность с мелкими дырочками). Пыльник отлично подходит для хранения вашей сумочки.</li></ul></div>"
    },
    {
      "id": 11,
      "title": "Бомбер (хлопок)",
      "image": ["catalog-11-1.webp", "catalog-11-2.webp", "catalog-11-3.jpg"],
      "price": 15500,
      "oldPrice": 0,
      "info": "Состав:60% хлопок 40% полиэстер",
      "categoryId": 3,
      "trendId": 0,
      "new": true,
      "popular": false,
      "measurements": "<p><strong>Параметры модели:</strong><br>ОГ &ndash; 87 см, ОТ &ndash; 61 см, ОБ - 89,5 см<br>Рост - 177 см<br><br><strong>Параметры изделия:</strong><br>ОГ &ndash; 126 см, ОТ &ndash; 148 см, ОБ - 132 см<br>Длина - 73 см, длина рукава - 60 см</p>",
      "care": "<p>- Не стирать<br>- Не отбеливать<br>- Температура утюга до 110 &deg;C<br>- Барабанная сушка запрещена<br>- Щадящая сухая чистка (химчистка)<br><br>Деликатный материал требует бережного обращения</p>"
    },
    {
      "id": 12,
      "title": "Бомбер CREATORE",
      "image": ["catalog-12-1.webp", "catalog-12-2.webp", "catalog-12-3.jpg"],
      "price": 12000,
      "oldPrice": 0,
      "info": "Сетчатый бомбер с полупрозрачными деталями. Основная часть изделия дополнена паттерном с логотипом бренда. Бомбер выполнен с молнией спереди. Манжеты по низу и на рукавах и воротник созданы в мелкий рубчик. Состав:50%хлопок 50%акрил",
      "categoryId": 3,
      "trendId": 6,
      "new": false,
      "popular": false,
      "measurements": "<p><strong>Параметры модели:</strong><br>ОГ &ndash; 87 см, ОТ &ndash; 61 см, ОБ - 89,5 см<br>Рост - 177 см<br><br><strong>Параметры изделия:</strong><br>ОГ &ndash; 126 см, ОТ &ndash; 148 см, ОБ - 132 см<br>Длина - 73 см, длина рукава - 60 см</p>",
      "care": "<p>- Не стирать<br>- Не отбеливать<br>- Температура утюга до 110 &deg;C<br>- Барабанная сушка запрещена<br>- Щадящая сухая чистка (химчистка)<br><br>Деликатный материал требует бережного обращения</p>"
    },
    {
      "id": 13,
      "title": "Бомбер двусторонний MOSCOVITE",
      "image": ["catalog-13-1.webp", "catalog-13-2.jpg", "catalog-13-3.jpg"],
      "price": 21400,
      "oldPrice": 42900,
      "info": "Двусторонний бомбер объемного силуэта из курточной ткани с влаго- и ветрозащитой. Декорирован двусторонним трикотажем из 100% шерсти. Принт - витраж используется в церковной архитектуре и в императорской архитектуре , а так же в светской. В принте мы совместили эту историческую технику и стиль городского теггинга , когда места наделяются своими персональными данными на двух сторонах бомбера. Основная ткань: 100% полиэстер утеплитель: 100% альполюкс",
      "categoryId": 3,
      "trendId": 0,
      "new": false,
      "popular": true,
      "measurements": "<p><strong>Параметры модели:</strong><br>ОГ &ndash; 87 см, ОТ &ndash; 61 см, ОБ - 89,5 см<br>Рост - 177 см<br><br><strong>Параметры изделия:</strong><br>ОГ &ndash; 126 см, ОТ &ndash; 148 см, ОБ - 132 см<br>Длина - 73 см, длина рукава - 60 см</p>",
      "care": "Стирка при 30 градусах или сухая чистка. Не сушить в центрифуге, не отбеливать. Бережная глажка при низкой температуре (до 110 градусов), отпариватель."
    },
    {
      "id": 14,
      "title": "Бомбер Street style",
      "image": ["catalog-14-1.webp", "catalog-14-2.webp", "catalog-14-3.webp"],
      "price": 18000,
      "oldPrice": 0,
      "info": "Бомбер крупной вязки с цветочным паттерном на молнии. У изделия спущена линия плеч, рукава умеренной ширины дополнены контрастными манжетами. Манжет по низу изделия контрастен и призван сузить силуэт. Состав: 50%меринос 50%акрил",
      "categoryId": 3,
      "trendId": 0,
      "new": true,
      "popular": false,
      "measurements": "<p><strong>Параметры модели:</strong><br>ОГ &ndash; 87 см, ОТ &ndash; 61 см, ОБ - 89,5 см<br>Рост - 177 см<br><br><strong>Параметры изделия:</strong><br>ОГ &ndash; 126 см, ОТ &ndash; 148 см, ОБ - 132 см<br>Длина - 73 см, длина рукава - 60 см</p>",
      "care": "<p>За шерстью (трикотажем) придется ухаживать особым образом. Просто забросить вещь в стиральную машину и забыть о ней не получится. Если придерживаться правил ухода, изделие будет служить вам верой и правдой не один год, сохранив при этом свой изначальный вид.<br><u>Как меня стирать</u></p><ul><li>Для шерстяных вещей подходит только деликатная ручная стирка. Однако сейчас большинство стиральных машин имеют специальные режимы ручной и деликатной стирки, а некоторые и специальную функцию &laquo;Стирка изделий из шерсти&raquo;;</li><li>Одежда из шерсти не терпит горячей воды. Температура стирки должна быть не выше 30&deg;. В противном случае вы рискуете получить вещь на несколько размеров меньше, утратившую первоначальный насыщенный цвет;</li><li>Откажитесь от агрессивных стиральных порошков. Лучше использовать специальные моющие средства для шерсти или шампунь. Для дорогих типов ткани (кашемир,&nbsp;альпака) отлично подойдет детский шампунь;</li><li>Не выкручивать, не замачивать надолго и не тереть. Всё, что вы можете сделать &mdash; это аккуратно отжать воду из изделия. Также запрещен режим сильного отжима при стирке в машине.</li></ul><p><u>Как меня сушить</u></p><ul><li>На горизонтальной поверхности - главное, что стоит знать о сушке шерстяных изделий. Вещь нужно разложить на полотенце вдали от прямых солнечных лучей и приборов отопления и позволить ей самой высохнуть при комнатной температуре;</li><li>Не стоит вешать шерстяные вещи, особенно свитера. В результате вас ждет растянутое, потерявшее вид изделие;</li><li>Поскольку шерсть склонна впитывать большое количество воды, можно осторожно завернуть вещь в полотенце (в рулон). Лишняя влага впитается в него.</li></ul><p><u>Как меня гладить</u></p><ul><li>Некоторые изделия из шерстяных тканей допускается гладить. Однако делать это следует через влажную материю с использованием таких режимов утюга, как &laquo;шерсть&raquo; или &laquo;функция увлажнения&raquo;;</li><li>При наличии на одежде лоснящихся участков, образовавшихся при длительной носке и трении, можно отпарить это место или воспользоваться жесткой щеткой.</li></ul>"
    },
    {
      "id": 15,
      "title": "Брюки BIZZI",
      "image": ["catalog-15-1.webp", "catalog-15-2.webp", "catalog-15-3.jpg"],
      "price": 13500,
      "oldPrice": 0,
      "info": "Состав: 60% подиэстер,35% високза,5% эластан",
      "categoryId": 4,
      "trendId": 1,
      "new": false,
      "popular": false,
      "measurements": "<p>XS (40-42)| 78-86 (Грудь)| 58-66 см (Талия)| 86-94 см (Бёдра)<br><u>S (42-44)</u>| 82-90 (Грудь)&nbsp;| 62-70 см (Талия)| 90-98 см&nbsp;(Бёдра)<br><u>M (44-46)</u>|&nbsp;86-94 (Грудь)&nbsp;|66-74 см (Талия)| 94-102 см&nbsp;(Бёдра)<br><u>L&nbsp;(46-48)</u>| 90-98 (Грудь)&nbsp;| 70-78 см (Талия)| 98-104 см&nbsp;(Бёдра)<br><u>XL&nbsp;(48-50)</u>| 94-102 (Грудь)&nbsp;| 74-82 см (Талия)| 102-110 см&nbsp;(Бёдра)<br><u>ONESIZE (42-48)</u>&nbsp;| 78-98 (Грудь)&nbsp;| 62-78 см (Талия)| 82-104см&nbsp;(Бёдра)</p>",
      "care": "<p>- Не стирать<br>- Не отбеливать<br>- Температура утюга до 110 &deg;C<br>- Барабанная сушка запрещена<br>- Щадящая сухая чистка (химчистка)<br><br>Деликатный материал требует бережного обращения</p>"
    },
    {
      "id": 16,
      "title": "Брюки POLOSKA",
      "image": ["catalog-16-1.webp", "catalog-16-2.webp", "catalog-16-3.webp"],
      "price": 7100,
      "oldPrice": 0,
      "info": "Цвета: голубой Размерный ряд: one size Состав: хлопок 100% Брюки из вываренного 100% хлопка. Талия на резинке. Спереди имитация гульфика.",
      "categoryId": 4,
      "trendId": 1,
      "new": false,
      "popular": true,
      "measurements": "<p>XS (40-42)| 78-86 (Грудь)| 58-66 см (Талия)| 86-94 см (Бёдра)<br><u>S (42-44)</u>| 82-90 (Грудь)&nbsp;| 62-70 см (Талия)| 90-98 см&nbsp;(Бёдра)<br><u>M (44-46)</u>|&nbsp;86-94 (Грудь)&nbsp;|66-74 см (Талия)| 94-102 см&nbsp;(Бёдра)<br><u>L&nbsp;(46-48)</u>| 90-98 (Грудь)&nbsp;| 70-78 см (Талия)| 98-104 см&nbsp;(Бёдра)<br><u>XL&nbsp;(48-50)</u>| 94-102 (Грудь)&nbsp;| 74-82 см (Талия)| 102-110 см&nbsp;(Бёдра)<br><u>ONESIZE (42-48)</u>&nbsp;| 78-98 (Грудь)&nbsp;| 62-78 см (Талия)| 82-104см&nbsp;(Бёдра)</p>",
      "care": "<p>Хлопковые ткани можно загружать в стиральную машину. Если ткань слишком тонка или вы дорожите ее цветом &ndash; лучше всего отстирать руками.<br><u>Как меня стирать</u></p><ul><li>Одежду нужно вывернуть наизнанку, это позволит сберечь внешний вид наружной стороны ткани;</li><li>Пуговицы и молнии застегнуть;</li><li>При стирке хлопчатой одежды необходимо соблюдать температурный режим и стирать при 30-40&deg;C;</li><li>Вещи из хлопка рекомендуется стирать отдельно от другой одежды, потому что этот материал во время стирки может растягиваться;</li><li>Если на изделии есть пятна, их лучше заранее вывести специальным средством</li></ul><p><u>Как меня сушить</u></p><ul><li>Вещи лучше не отжимать или делать это максимально щадяще;</li><li>Вывешивайте одежду сразу после стирки, это позволит придать вещам максимальную формостойкость и избежать помятостей;</li><li>Сушить лучше всего только в тех местах, где исключено прямое попадание солнечных лучей на одежду.</li></ul><p><u>Как меня гладить</u></p><ul><li>Гладить одежду нужно с изнаночной стороны;</li><li>Перед глажкой тонкого изделия лучше проверить устойчивость к высоким температурам на незаметном участке;</li><li>Главное &ndash; не пересушить хлопок. Если не удалось избежать этого неприятного явления, то перед тем как гладить, можно сбрызнуть слегка водой;</li><li>Чтобы предотвратить растягивание, водить утюгом нужно вдоль.</li></ul>"
    },
    {
      "id": 17,
      "title": "Брюки Ariel (футер)",
      "image": ["catalog-17-1.webp", "catalog-17-2.webp", "catalog-17-3.jpg"],
      "price": 6800,
      "oldPrice": 0,
      "info": "Состав:85% хлопок 15% полиэстер",
      "categoryId": 4,
      "trendId": 3,
      "new": false,
      "popular": false,
      "measurements": "<p>XS (40-42)| 78-86 (Грудь)| 58-66 см (Талия)| 86-94 см (Бёдра)<br><u>S (42-44)</u>| 82-90 (Грудь)&nbsp;| 62-70 см (Талия)| 90-98 см&nbsp;(Бёдра)<br><u>M (44-46)</u>|&nbsp;86-94 (Грудь)&nbsp;|66-74 см (Талия)| 94-102 см&nbsp;(Бёдра)<br><u>L&nbsp;(46-48)</u>| 90-98 (Грудь)&nbsp;| 70-78 см (Талия)| 98-104 см&nbsp;(Бёдра)<br><u>XL&nbsp;(48-50)</u>| 94-102 (Грудь)&nbsp;| 74-82 см (Талия)| 102-110 см&nbsp;(Бёдра)<br><u>ONESIZE (42-48)</u>&nbsp;| 78-98 (Грудь)&nbsp;| 62-78 см (Талия)| 82-104см&nbsp;(Бёдра)</p>",
      "care": "<p>Хлопковые ткани можно загружать в стиральную машину. Если ткань слишком тонка или вы дорожите ее цветом &ndash; лучше всего отстирать руками.<br><u>Как меня стирать</u></p><ul><li>Одежду нужно вывернуть наизнанку, это позволит сберечь внешний вид наружной стороны ткани;</li><li>Пуговицы и молнии застегнуть;</li><li>При стирке хлопчатой одежды необходимо соблюдать температурный режим и стирать при 30-40&deg;C;</li><li>Вещи из хлопка рекомендуется стирать отдельно от другой одежды, потому что этот материал во время стирки может растягиваться;</li><li>Если на изделии есть пятна, их лучше заранее вывести специальным средством</li></ul><p><u>Как меня сушить</u></p><ul><li>Вещи лучше не отжимать или делать это максимально щадяще;</li><li>Вывешивайте одежду сразу после стирки, это позволит придать вещам максимальную формостойкость и избежать помятостей;</li><li>Сушить лучше всего только в тех местах, где исключено прямое попадание солнечных лучей на одежду.</li></ul><p><u>Как меня гладить</u></p><ul><li>Гладить одежду нужно с изнаночной стороны;</li><li>Перед глажкой тонкого изделия лучше проверить устойчивость к высоким температурам на незаметном участке;</li><li>Главное &ndash; не пересушить хлопок. Если не удалось избежать этого неприятного явления, то перед тем как гладить, можно сбрызнуть слегка водой;</li><li>Чтобы предотвратить растягивание, водить утюгом нужно вдоль.</li></ul>"
    },
    {
      "id": 18,
      "title": "Брюки на резинке Sandra",
      "image": ["catalog-18-1.webp", "catalog-18-2.webp", "catalog-18-3.jpg"],
      "price": 9250,
      "oldPrice": 0,
      "info": "Состав:57% вискоза 31% полиэстер 5% шерсть 5% лиоцел 2% спандекс",
      "categoryId": 4,
      "trendId": 3,
      "new": false,
      "popular": false,
      "measurements": "<p>XS (40-42)| 78-86 (Грудь)| 58-66 см (Талия)| 86-94 см (Бёдра)<br><u>S (42-44)</u>| 82-90 (Грудь)&nbsp;| 62-70 см (Талия)| 90-98 см&nbsp;(Бёдра)<br><u>M (44-46)</u>|&nbsp;86-94 (Грудь)&nbsp;|66-74 см (Талия)| 94-102 см&nbsp;(Бёдра)<br><u>L&nbsp;(46-48)</u>| 90-98 (Грудь)&nbsp;| 70-78 см (Талия)| 98-104 см&nbsp;(Бёдра)<br><u>XL&nbsp;(48-50)</u>| 94-102 (Грудь)&nbsp;| 74-82 см (Талия)| 102-110 см&nbsp;(Бёдра)<br><u>ONESIZE (42-48)</u>&nbsp;| 78-98 (Грудь)&nbsp;| 62-78 см (Талия)| 82-104см&nbsp;(Бёдра)</p>",
      "care": "<div><div>При использовании слишком концентрированного или неподходящего моющего средства, может пострадать цвет изделия. А неаккуратная ручная стирка приведёт к порче структуры ткани.<br><u>Как меня стирать</u><br><ul><li>Рекомендуем ручную стирку;</li><li>При стирке в стиральной машине, необходимо выбрать деликатный режим. Вещи из вискозы можно стирать только при 30&deg;C;</li><li>Ни в коем случае нельзя выжимать вискозу в машинке, так как после этого она садится;</li><li>Необходимо использовать порошок для тонких тканей;</li><li>При стирке вещей из вискозы в стиральной машине, рекомендуем также использовать специальный мешочек.</li><li>Лучше всего изделия из вискозы не выкручивать, а отжимать в полотенце.</li><li>Изделия можно оставить сохнуть на плечиках. Они должны быть обтянуты мягкой тканью или поролоном, чтоб избежать деформаций и некрасивых изгибов.</li></ul><u>Как меня сушить</u><br><ul><li>Лучше всего изделия из вискозы не выкручивать, а отжимать в полотенце.</li><li>Изделия можно оставить сохнуть на плечиках. Они должны быть обтянуты мягкой тканью или поролоном, чтоб избежать деформаций и некрасивых изгибов.</li></ul><u>Как меня гладить</u><br><ul><li>Выбирайте температурный режим &ndash; &laquo;Шелк&raquo;, отпаривать изделия не рекомендуется;</li><li>Изделия из вискозы гладить влажными, используя деликатный режим;</li><li>Полностью сухие вещи лучше гладить наизнанку, через мокрую марлю или другую тонкую ткань.</li></ul></div></div>"
    },
    {
      "id": 19,
      "title": "Брюки широкие без боковых швов шитье",
      "image": ["catalog-19-1.webp", "catalog-19-2.webp", "catalog-19-3.webp"],
      "price": 14900,
      "oldPrice": 0,
      "info": "Свободные легкие брюки на кулиске из дышащей хлопковой ткани с геометричной вышивкой. Состав: 100% хлопок",
      "categoryId": 4,
      "trendId": 5,
      "new": false,
      "popular": false,
      "measurements": "<p>XS (40-42)| 78-86 (Грудь)| 58-66 см (Талия)| 86-94 см (Бёдра)<br><u>S (42-44)</u>| 82-90 (Грудь)&nbsp;| 62-70 см (Талия)| 90-98 см&nbsp;(Бёдра)<br><u>M (44-46)</u>|&nbsp;86-94 (Грудь)&nbsp;|66-74 см (Талия)| 94-102 см&nbsp;(Бёдра)<br><u>L&nbsp;(46-48)</u>| 90-98 (Грудь)&nbsp;| 70-78 см (Талия)| 98-104 см&nbsp;(Бёдра)<br><u>XL&nbsp;(48-50)</u>| 94-102 (Грудь)&nbsp;| 74-82 см (Талия)| 102-110 см&nbsp;(Бёдра)<br><u>ONESIZE (42-48)</u>&nbsp;| 78-98 (Грудь)&nbsp;| 62-78 см (Талия)| 82-104см&nbsp;(Бёдра)</p>",
      "care": "<p>Хлопковые ткани можно загружать в стиральную машину. Если ткань слишком тонка или вы дорожите ее цветом &ndash; лучше всего отстирать руками.<br><u>Как меня стирать</u></p><ul><li>Одежду нужно вывернуть наизнанку, это позволит сберечь внешний вид наружной стороны ткани;</li><li>Пуговицы и молнии застегнуть;</li><li>При стирке хлопчатой одежды необходимо соблюдать температурный режим и стирать при 30-40&deg;C;</li><li>Вещи из хлопка рекомендуется стирать отдельно от другой одежды, потому что этот материал во время стирки может растягиваться;</li><li>Если на изделии есть пятна, их лучше заранее вывести специальным средством</li></ul><p><u>Как меня сушить</u></p><ul><li>Вещи лучше не отжимать или делать это максимально щадяще;</li><li>Вывешивайте одежду сразу после стирки, это позволит придать вещам максимальную формостойкость и избежать помятостей;</li><li>Сушить лучше всего только в тех местах, где исключено прямое попадание солнечных лучей на одежду.</li></ul><p><u>Как меня гладить</u></p><ul><li>Гладить одежду нужно с изнаночной стороны;</li><li>Перед глажкой тонкого изделия лучше проверить устойчивость к высоким температурам на незаметном участке;</li><li>Главное &ndash; не пересушить хлопок. Если не удалось избежать этого неприятного явления, то перед тем как гладить, можно сбрызнуть слегка водой;</li><li>Чтобы предотвратить растягивание, водить утюгом нужно вдоль.</li></ul>"
    },
    {
      "id": 20,
      "title": "Брюки-палаццо",
      "image": ["catalog-20-1.jpg", "catalog-20-2.webp", "catalog-20-3.jpg"],
      "price": 11300,
      "oldPrice": 0,
      "info": "Ткань плательная, плотная, хорошо драпирующаяся. Прямые по всей длине. По 2ве складки по передних половинках брюк -боковые, наклонные, функциональные карманы. Высокая посадка (до линии талии). Пояс по верхней части брюк. Застежка на брючную молнию, крючок и петлю с потайной пуговицей. По левой задней половинке брюк под выточкой -карман в листочку, нефункциональный. СОСТАВ Брюки: 100% полиэстер Подклад: 48% вискоза, 52% полиэстер",
      "categoryId": 4,
      "trendId": 6,
      "new": false,
      "popular": true,
      "measurements": "<p>XS (40-42)| 78-86 (Грудь)| 58-66 см (Талия)| 86-94 см (Бёдра)<br><u>S (42-44)</u>| 82-90 (Грудь)&nbsp;| 62-70 см (Талия)| 90-98 см&nbsp;(Бёдра)<br><u>M (44-46)</u>|&nbsp;86-94 (Грудь)&nbsp;|66-74 см (Талия)| 94-102 см&nbsp;(Бёдра)<br><u>L&nbsp;(46-48)</u>| 90-98 (Грудь)&nbsp;| 70-78 см (Талия)| 98-104 см&nbsp;(Бёдра)<br><u>XL&nbsp;(48-50)</u>| 94-102 (Грудь)&nbsp;| 74-82 см (Талия)| 102-110 см&nbsp;(Бёдра)<br><u>ONESIZE (42-48)</u>&nbsp;| 78-98 (Грудь)&nbsp;| 62-78 см (Талия)| 82-104см&nbsp;(Бёдра)</p>",
      "care": "<p>При использовании слишком концентрированного или неподходящего моющего средства, может пострадать цвет изделия. А неаккуратная ручная стирка приведёт к порче структуры ткани.<br><u>Как меня стирать</u></p><ul><li>Рекомендуем ручную стирку;</li><li>При стирке в стиральной машине, необходимо выбрать деликатный режим. Вещи из вискозы можно стирать только при 30&deg;C;</li><li>Ни в коем случае нельзя выжимать вискозу в машинке, так как после этого она садится;</li><li>Необходимо использовать порошок для тонких тканей;</li><li>При стирке вещей из вискозы в стиральной машине, рекомендуем также использовать специальный мешочек.</li><li>Лучше всего изделия из вискозы не выкручивать, а отжимать в полотенце.</li><li>Изделия можно оставить сохнуть на плечиках. Они должны быть обтянуты мягкой тканью или поролоном, чтоб избежать деформаций и некрасивых изгибов.</li></ul><p><u>Как меня сушить</u></p><ul><li>Лучше всего изделия из вискозы не выкручивать, а отжимать в полотенце.</li><li>Изделия можно оставить сохнуть на плечиках. Они должны быть обтянуты мягкой тканью или поролоном, чтоб избежать деформаций и некрасивых изгибов.</li></ul><p><u>Как меня гладить</u></p><ul><li>Выбирайте температурный режим &ndash; &laquo;Шелк&raquo;, отпаривать изделия не рекомендуется;</li><li>Изделия из вискозы гладить влажными, используя деликатный режим;</li><li>Полностью сухие вещи лучше гладить наизнанку, через мокрую марлю или другую тонкую ткань.</li></ul>"
    },
    {
      "id": 21,
      "title": "Платье ROZI",
      "image": ["catalog-21-1.webp", "catalog-21-2.webp", "catalog-21-3.jpg"],
      "price": 18500,
      "oldPrice": 0,
      "info": "Состав: 80% п/э,15% вискоза,5% спандекс",
      "categoryId": 5,
      "trendId": 2,
      "new": false,
      "popular": false,
      "measurements": "<p>XS (40-42)| 78-86 (Грудь)| 58-66 см (Талия)| 86-94 см (Бёдра)<br><u>S (42-44)</u>| 82-90 (Грудь)&nbsp;| 62-70 см (Талия)| 90-98 см&nbsp;(Бёдра)<br><u>M (44-46)</u>|&nbsp;86-94 (Грудь)&nbsp;|66-74 см (Талия)| 94-102 см&nbsp;(Бёдра)<br><u>L&nbsp;(46-48)</u>| 90-98 (Грудь)&nbsp;| 70-78 см (Талия)| 98-104 см&nbsp;(Бёдра)<br><u>XL&nbsp;(48-50)</u>| 94-102 (Грудь)&nbsp;| 74-82 см (Талия)| 102-110 см&nbsp;(Бёдра)<br><u>ONESIZE (42-48)</u>&nbsp;| 78-98 (Грудь)&nbsp;| 62-78 см (Талия)| 82-104см&nbsp;(Бёдра)</p>",
      "care": "<p>- Не стирать<br>- Не отбеливать<br>- Температура утюга до 110 &deg;C<br>- Барабанная сушка запрещена<br>- Щадящая сухая чистка (химчистка)<br><br>Деликатный материал требует бережного обращения</p>"
    },
    {
      "id": 22,
      "title": "Платье LANA",
      "image": ["catalog-22-1.webp", "catalog-22-2.webp", "catalog-22-3.webp"],
      "price": 29100,
      "oldPrice": 0,
      "info": "Состав: 96% п/э,4% эластан",
      "categoryId": 5,
      "trendId": 2,
      "new": false,
      "popular": false,
      "measurements": "<p>XS (40-42)| 78-86 (Грудь)| 58-66 см (Талия)| 86-94 см (Бёдра)<br><u>S (42-44)</u>| 82-90 (Грудь)&nbsp;| 62-70 см (Талия)| 90-98 см&nbsp;(Бёдра)<br><u>M (44-46)</u>|&nbsp;86-94 (Грудь)&nbsp;|66-74 см (Талия)| 94-102 см&nbsp;(Бёдра)<br><u>L&nbsp;(46-48)</u>| 90-98 (Грудь)&nbsp;| 70-78 см (Талия)| 98-104 см&nbsp;(Бёдра)<br><u>XL&nbsp;(48-50)</u>| 94-102 (Грудь)&nbsp;| 74-82 см (Талия)| 102-110 см&nbsp;(Бёдра)<br><u>ONESIZE (42-48)</u>&nbsp;| 78-98 (Грудь)&nbsp;| 62-78 см (Талия)| 82-104см&nbsp;(Бёдра)</p>",
      "care": "<p>- Не стирать<br>- Не отбеливать<br>- Температура утюга до 110 &deg;C<br>- Барабанная сушка запрещена<br>- Щадящая сухая чистка (химчистка)<br><br>Деликатный материал требует бережного обращения</p>"
    },
    {
      "id": 23,
      "title": "Платье Crochet",
      "image": ["catalog-23-1.webp", "catalog-23-2.webp", "catalog-23-3.webp"],
      "price": 7200,
      "oldPrice": 0,
      "info": "Состав: 100% хлопок",
      "categoryId": 5,
      "trendId": 3,
      "new": true,
      "popular": false,
      "measurements": "<p>XS (40-42)| 78-86 (Грудь)| 58-66 см (Талия)| 86-94 см (Бёдра)<br><u>S (42-44)</u>| 82-90 (Грудь)&nbsp;| 62-70 см (Талия)| 90-98 см&nbsp;(Бёдра)<br><u>M (44-46)</u>|&nbsp;86-94 (Грудь)&nbsp;|66-74 см (Талия)| 94-102 см&nbsp;(Бёдра)<br><u>L&nbsp;(46-48)</u>| 90-98 (Грудь)&nbsp;| 70-78 см (Талия)| 98-104 см&nbsp;(Бёдра)<br><u>XL&nbsp;(48-50)</u>| 94-102 (Грудь)&nbsp;| 74-82 см (Талия)| 102-110 см&nbsp;(Бёдра)<br><u>ONESIZE (42-48)</u>&nbsp;| 78-98 (Грудь)&nbsp;| 62-78 см (Талия)| 82-104см&nbsp;(Бёдра)</p>",
      "care": "<p>Хлопковые ткани можно загружать в стиральную машину. Если ткань слишком тонка или вы дорожите ее цветом &ndash; лучше всего отстирать руками.<br><u>Как меня стирать</u></p><ul><li>Одежду нужно вывернуть наизнанку, это позволит сберечь внешний вид наружной стороны ткани;</li><li>Пуговицы и молнии застегнуть;</li><li>При стирке хлопчатой одежды необходимо соблюдать температурный режим и стирать при 30-40&deg;C;</li><li>Вещи из хлопка рекомендуется стирать отдельно от другой одежды, потому что этот материал во время стирки может растягиваться;</li><li>Если на изделии есть пятна, их лучше заранее вывести специальным средством</li></ul><p><u>Как меня сушить</u></p><ul><li>Вещи лучше не отжимать или делать это максимально щадяще;</li><li>Вывешивайте одежду сразу после стирки, это позволит придать вещам максимальную формостойкость и избежать помятостей;</li><li>Сушить лучше всего только в тех местах, где исключено прямое попадание солнечных лучей на одежду.</li></ul><p><u>Как меня гладить</u></p><ul><li>Гладить одежду нужно с изнаночной стороны;</li><li>Перед глажкой тонкого изделия лучше проверить устойчивость к высоким температурам на незаметном участке;</li><li>Главное &ndash; не пересушить хлопок. Если не удалось избежать этого неприятного явления, то перед тем как гладить, можно сбрызнуть слегка водой;</li><li>Чтобы предотвратить растягивание, водить утюгом нужно вдоль.</li></ul>"
    },
    {
      "id": 24,
      "title": "Платье Boho foam цвета экрю",
      "image": ["catalog-24-1.webp", "catalog-24-2.webp", "catalog-24-3.webp"],
      "price": 17700,
      "oldPrice": 0,
      "info": "Свободное платье макси длины. Изделие выполнено из легкой ажурной ткани, которая мягко ложится по фигуре. Глубокий боковой разрез добавляет образу игривости и подчеркивает силуэт. Мой тебе совет, для расслабленного образа носите его как удлинённый топ с монохромными брюками, а для эффектного выхода — позвольте платью заиграть самостоятельно, дополнив его яркими аксессуарами. Рост и параметры модели на фото 168 78-58-92",
      "categoryId": 5,
      "trendId": 5,
      "new": false,
      "popular": false,
      "measurements": "<p>XS (40-42)| 78-86 (Грудь)| 58-66 см (Талия)| 86-94 см (Бёдра)<br><u>S (42-44)</u>| 82-90 (Грудь)&nbsp;| 62-70 см (Талия)| 90-98 см&nbsp;(Бёдра)<br><u>M (44-46)</u>|&nbsp;86-94 (Грудь)&nbsp;|66-74 см (Талия)| 94-102 см&nbsp;(Бёдра)<br><u>L&nbsp;(46-48)</u>| 90-98 (Грудь)&nbsp;| 70-78 см (Талия)| 98-104 см&nbsp;(Бёдра)<br><u>XL&nbsp;(48-50)</u>| 94-102 (Грудь)&nbsp;| 74-82 см (Талия)| 102-110 см&nbsp;(Бёдра)<br><u>ONESIZE (42-48)</u>&nbsp;| 78-98 (Грудь)&nbsp;| 62-78 см (Талия)| 82-104см&nbsp;(Бёдра)</p>",
      "care": "<p><strong>Материал</strong>&nbsp;100% Полиэстер<br><strong>Инструкции по уходу</strong>&nbsp;Ручная стирка до 30&deg;C. Не отжимать. Не сушить в сушильной машине. Не отбеливать. Гладить утюгом при низкой температуре или отпаривателем. Не подвергать химчистке.</p>"
    },
    {
      "id": 25,
      "title": "Платье Mistero",
      "image": ["catalog-25-1.webp", "catalog-25-2.jpg", "catalog-25-3.webp"],
      "price": 12000,
      "oldPrice": 0,
      "info": "Платье приталенного силуэта мелкой вязки с цветочным узором и вырезом на спине. Рукава слегка расклешаются у кистей. Изделие однослойное без подклада. Состав:50%меринос 50%акрил",
      "categoryId": 5,
      "trendId": 5,
      "new": false,
      "popular": true,
      "measurements": "<p>XS (40-42)| 78-86 (Грудь)| 58-66 см (Талия)| 86-94 см (Бёдра)<br><u>S (42-44)</u>| 82-90 (Грудь)&nbsp;| 62-70 см (Талия)| 90-98 см&nbsp;(Бёдра)<br><u>M (44-46)</u>|&nbsp;86-94 (Грудь)&nbsp;|66-74 см (Талия)| 94-102 см&nbsp;(Бёдра)<br><u>L&nbsp;(46-48)</u>| 90-98 (Грудь)&nbsp;| 70-78 см (Талия)| 98-104 см&nbsp;(Бёдра)<br><u>XL&nbsp;(48-50)</u>| 94-102 (Грудь)&nbsp;| 74-82 см (Талия)| 102-110 см&nbsp;(Бёдра)<br><u>ONESIZE (42-48)</u>&nbsp;| 78-98 (Грудь)&nbsp;| 62-78 см (Талия)| 82-104см&nbsp;(Бёдра)</p>",
      "care": "<p>За шерстью (трикотажем) придется ухаживать особым образом. Просто забросить вещь в стиральную машину и забыть о ней не получится. Если придерживаться правил ухода, изделие будет служить вам верой и правдой не один год, сохранив при этом свой изначальный вид.<br><u>Как меня стирать</u></p><ul><li>Для шерстяных вещей подходит только деликатная ручная стирка. Однако сейчас большинство стиральных машин имеют специальные режимы ручной и деликатной стирки, а некоторые и специальную функцию &laquo;Стирка изделий из шерсти&raquo;;</li><li>Одежда из шерсти не терпит горячей воды. Температура стирки должна быть не выше 30&deg;. В противном случае вы рискуете получить вещь на несколько размеров меньше, утратившую первоначальный насыщенный цвет;</li><li>Откажитесь от агрессивных стиральных порошков. Лучше использовать специальные моющие средства для шерсти или шампунь. Для дорогих типов ткани (кашемир,&nbsp;альпака) отлично подойдет детский шампунь;</li><li>Не выкручивать, не замачивать надолго и не тереть. Всё, что вы можете сделать &mdash; это аккуратно отжать воду из изделия. Также запрещен режим сильного отжима при стирке в машине.</li></ul><p><u>Как меня сушить</u></p><ul><li>На горизонтальной поверхности - главное, что стоит знать о сушке шерстяных изделий. Вещь нужно разложить на полотенце вдали от прямых солнечных лучей и приборов отопления и позволить ей самой высохнуть при комнатной температуре;</li><li>Не стоит вешать шерстяные вещи, особенно свитера. В результате вас ждет растянутое, потерявшее вид изделие;</li><li>Поскольку шерсть склонна впитывать большое количество воды, можно осторожно завернуть вещь в полотенце (в рулон). Лишняя влага впитается в него.</li></ul><p><u>Как меня гладить</u></p><ul><li>Некоторые изделия из шерстяных тканей допускается гладить. Однако делать это следует через влажную материю с использованием таких режимов утюга, как &laquo;шерсть&raquo; или &laquo;функция увлажнения&raquo;;</li><li>При наличии на одежде лоснящихся участков, образовавшихся при длительной носке и трении, можно отпарить это место или воспользоваться жесткой щеткой.</li></ul>"
    },
    {
      "id": 26,
      "title": "Платье макси без рукавов",
      "image": ["catalog-26-1.webp", "catalog-26-2.webp", "catalog-26-3.webp"],
      "price": 10000,
      "oldPrice": 0,
      "info": "Состав:97% полиэстер,3% эластан",
      "categoryId": 5,
      "trendId": 5,
      "new": false,
      "popular": false,
      "measurements": "<p>XS (40-42)| 78-86 (Грудь)| 58-66 см (Талия)| 86-94 см (Бёдра)<br><u>S (42-44)</u>| 82-90 (Грудь)&nbsp;| 62-70 см (Талия)| 90-98 см&nbsp;(Бёдра)<br><u>M (44-46)</u>|&nbsp;86-94 (Грудь)&nbsp;|66-74 см (Талия)| 94-102 см&nbsp;(Бёдра)<br><u>L&nbsp;(46-48)</u>| 90-98 (Грудь)&nbsp;| 70-78 см (Талия)| 98-104 см&nbsp;(Бёдра)<br><u>XL&nbsp;(48-50)</u>| 94-102 (Грудь)&nbsp;| 74-82 см (Талия)| 102-110 см&nbsp;(Бёдра)<br><u>ONESIZE (42-48)</u>&nbsp;| 78-98 (Грудь)&nbsp;| 62-78 см (Талия)| 82-104см&nbsp;(Бёдра)</p>",
      "care": "<p>Отличительная особенность синтетических тканей заключается в том, что они прочны, меньше мнутся и могут прослужить более длительное время.<br><u>Как меня стирать</u></p><ul><li>Стирать максимум при 30&deg;C;</li><li>Не отжимать на высоких оборотах (образуются заломы, которые трудно или невозможно разгладить);</li><li>При стирке вручную, загрязненные места, нельзя тереть с силой, так как могут деформироваться волокна;</li><li>Не выкручивать мокрые вещи. Лучше всего аккуратно выжать в полотенце.</li></ul><p><u>Как меня сушить</u></p><ul><li>Достаточно аккуратно выжать изделие и выложить на горизонтальной поверхности.</li></ul><p><u>Как меня гладить</u></p><ul><li>Полиэстер обладает свойством распрямляться. Если складки все-таки есть, то гладить синтетические волокна необходимо с изнанки, при температуре от 100&deg;C до 200&deg;C с использованием влажной ткани.</li></ul>"
    },
    {
      "id": 27,
      "title": "Пиджак Bella",
      "image": ["catalog-27-1.webp", "catalog-27-2.webp", "catalog-27-3.jpg"],
      "price": 22100,
      "oldPrice": 0,
      "info": "Жакет и юбка-шорты с подкладой бордового оттенка выполнены из премиальной костюмной ткани. Выверенная посадка и талиевые вытачки изящно подчеркивают силуэт. Состав: 60% подиэстер,35% високза,5% эластан",
      "categoryId": 6,
      "trendId": 1,
      "new": false,
      "popular": false,
      "measurements": "<p>XS (40-42)| 78-86 (Грудь)| 58-66 см (Талия)| 86-94 см (Бёдра)<br><u>S (42-44)</u>| 82-90 (Грудь)&nbsp;| 62-70 см (Талия)| 90-98 см&nbsp;(Бёдра)<br><u>M (44-46)</u>|&nbsp;86-94 (Грудь)&nbsp;|66-74 см (Талия)| 94-102 см&nbsp;(Бёдра)<br><u>L&nbsp;(46-48)</u>| 90-98 (Грудь)&nbsp;| 70-78 см (Талия)| 98-104 см&nbsp;(Бёдра)<br><u>XL&nbsp;(48-50)</u>| 94-102 (Грудь)&nbsp;| 74-82 см (Талия)| 102-110 см&nbsp;(Бёдра)<br><u>ONESIZE (42-48)</u>&nbsp;| 78-98 (Грудь)&nbsp;| 62-78 см (Талия)| 82-104см&nbsp;(Бёдра)</p>",
      "care": "<p>- Не стирать<br>- Не отбеливать<br>- Температура утюга до 110 &deg;C<br>- Барабанная сушка запрещена<br>- Щадящая сухая чистка (химчистка)<br><br>Деликатный материал требует бережного обращения</p>"
    },
    {
      "id": 28,
      "title": "Пиджак BIZZI",
      "image": ["catalog-28-1.webp", "catalog-28-2.webp", "catalog-28-3.jpg"],
      "price": 19500,
      "oldPrice": 0,
      "info": "Состав: 60% подиэстер,35% високза,5% эластан",
      "categoryId": 6,
      "trendId": 1,
      "new": true,
      "popular": false,
      "measurements": "<p>XS (40-42)| 78-86 (Грудь)| 58-66 см (Талия)| 86-94 см (Бёдра)<br><u>S (42-44)</u>| 82-90 (Грудь)&nbsp;| 62-70 см (Талия)| 90-98 см&nbsp;(Бёдра)<br><u>M (44-46)</u>|&nbsp;86-94 (Грудь)&nbsp;|66-74 см (Талия)| 94-102 см&nbsp;(Бёдра)<br><u>L&nbsp;(46-48)</u>| 90-98 (Грудь)&nbsp;| 70-78 см (Талия)| 98-104 см&nbsp;(Бёдра)<br><u>XL&nbsp;(48-50)</u>| 94-102 (Грудь)&nbsp;| 74-82 см (Талия)| 102-110 см&nbsp;(Бёдра)<br><u>ONESIZE (42-48)</u>&nbsp;| 78-98 (Грудь)&nbsp;| 62-78 см (Талия)| 82-104см&nbsp;(Бёдра)</p>",
      "care": "<p>- Не стирать<br>- Не отбеливать<br>- Температура утюга до 110 &deg;C<br>- Барабанная сушка запрещена<br>- Щадящая сухая чистка (химчистка)<br><br>Деликатный материал требует бережного обращения</p>"
    },
    {
      "id": 29,
      "title": "Пиджак Sandra",
      "image": ["catalog-29-1.webp", "catalog-29-2.webp", "catalog-29-3.jpg"],
      "price": 14800,
      "oldPrice": 0,
      "info": "Состав:57% вискоза 31% полиэстер 5% шерсть 5% лиоцел 2% спандекс",
      "categoryId": 6,
      "trendId": 3,
      "new": false,
      "popular": false,
      "measurements": "<p>XS (40-42)| 78-86 (Грудь)| 58-66 см (Талия)| 86-94 см (Бёдра)<br><u>S (42-44)</u>| 82-90 (Грудь)&nbsp;| 62-70 см (Талия)| 90-98 см&nbsp;(Бёдра)<br><u>M (44-46)</u>|&nbsp;86-94 (Грудь)&nbsp;|66-74 см (Талия)| 94-102 см&nbsp;(Бёдра)<br><u>L&nbsp;(46-48)</u>| 90-98 (Грудь)&nbsp;| 70-78 см (Талия)| 98-104 см&nbsp;(Бёдра)<br><u>XL&nbsp;(48-50)</u>| 94-102 (Грудь)&nbsp;| 74-82 см (Талия)| 102-110 см&nbsp;(Бёдра)<br><u>ONESIZE (42-48)</u>&nbsp;| 78-98 (Грудь)&nbsp;| 62-78 см (Талия)| 82-104см&nbsp;(Бёдра)</p>",
      "care": "<p>- Не стирать<br>- Не отбеливать<br>- Температура утюга до 110 &deg;C<br>- Барабанная сушка запрещена<br>- Щадящая сухая чистка (химчистка)<br><br>Деликатный материал требует бережного обращения</p>"
    },
    {
      "id": 30,
      "title": "Пиджак KELLY",
      "image": ["catalog-30-1.webp", "catalog-30-2.jpg", "catalog-30-3.webp"],
      "price": 25000,
      "oldPrice": 0,
      "info": "Приталенный жакет черного цвета – прекрасное дополнение вашего базового выходного гардероба. Жакет из премиальной костюмной ткани выгодно подчеркивает фигуру благодаря приталенному силуэту и особому крою, который создают эффект 'песочные часы'. Ярким акцентом изделия стала открытая спинка, которая подчеркнет женственность и хрупкость фигуры. Советуем сочетать модель с парными брюками или юбкой-макси на выбор. Состав:100% полиэстер",
      "categoryId": 6,
      "trendId": 0,
      "new": false,
      "popular": false,
      "measurements": "<p>XS (40-42)| 78-86 (Грудь)| 58-66 см (Талия)| 86-94 см (Бёдра)<br><u>S (42-44)</u>| 82-90 (Грудь)&nbsp;| 62-70 см (Талия)| 90-98 см&nbsp;(Бёдра)<br><u>M (44-46)</u>|&nbsp;86-94 (Грудь)&nbsp;|66-74 см (Талия)| 94-102 см&nbsp;(Бёдра)<br><u>L&nbsp;(46-48)</u>| 90-98 (Грудь)&nbsp;| 70-78 см (Талия)| 98-104 см&nbsp;(Бёдра)<br><u>XL&nbsp;(48-50)</u>| 94-102 (Грудь)&nbsp;| 74-82 см (Талия)| 102-110 см&nbsp;(Бёдра)<br><u>ONESIZE (42-48)</u>&nbsp;| 78-98 (Грудь)&nbsp;| 62-78 см (Талия)| 82-104см&nbsp;(Бёдра)</p>",
      "care": "<p>- Не стирать<br>- Не отбеливать<br>- Температура утюга до 110 &deg;C<br>- Барабанная сушка запрещена<br>- Щадящая сухая чистка (химчистка)<br><br>Деликатный материал требует бережного обращения</p>"
    },
    {
      "id": 31,
      "title": "Пиджак 'Приданое'",
      "image": ["catalog-31-1.webp", "catalog-31-2.webp", "catalog-31-3.jpg"],
      "price": 49100,
      "oldPrice": 0,
      "info": "Новое сияющее прочтение классического пиджака. Выверенный крой дополняет инкрустация стразами. Пиджак выполнен из костюмного полотна, который благодаря добавлению искусственных волокон хорошо держит форму и меньше изнашивается со временем. Комбинируйте с брюками из нашей коллекции. На подкладке. Состав:65% полиэстер, 32% вискоза, 3% спандекс.",
      "categoryId": 6,
      "trendId": 0,
      "new": false,
      "popular": true,
      "measurements": "<p>XS (40-42)| 78-86 (Грудь)| 58-66 см (Талия)| 86-94 см (Бёдра)<br><u>S (42-44)</u>| 82-90 (Грудь)&nbsp;| 62-70 см (Талия)| 90-98 см&nbsp;(Бёдра)<br><u>M (44-46)</u>|&nbsp;86-94 (Грудь)&nbsp;|66-74 см (Талия)| 94-102 см&nbsp;(Бёдра)<br><u>L&nbsp;(46-48)</u>| 90-98 (Грудь)&nbsp;| 70-78 см (Талия)| 98-104 см&nbsp;(Бёдра)<br><u>XL&nbsp;(48-50)</u>| 94-102 (Грудь)&nbsp;| 74-82 см (Талия)| 102-110 см&nbsp;(Бёдра)<br><u>ONESIZE (42-48)</u>&nbsp;| 78-98 (Грудь)&nbsp;| 62-78 см (Талия)| 82-104см&nbsp;(Бёдра)</p>",
      "care": "<p>- Не стирать<br>- Не отбеливать<br>- Температура утюга до 110 &deg;C<br>- Барабанная сушка запрещена<br>- Щадящая сухая чистка (химчистка)<br><br>Деликатный материал требует бережного обращения</p>"
    },
    {
      "id": 32,
      "title": "Пиджак комби с джинсой",
      "image": ["catalog-32-1.webp", "catalog-32-2.jpg"],
      "price": 17800,
      "oldPrice": 26400,
      "info": "Пиджак женский OVERSIZE удлиненный прямого кроя из плотной костюмной ткани с декоративными голубыми вставками из джинсы. На модели размер: M-L Параметры модели: Рост 181 Объём 90/63/94 Основная ткань: 60% вискоза, 35% полиэстер, 5% эластан.",
      "categoryId": 6,
      "trendId": 0,
      "new": false,
      "popular": true,
      "measurements": "<p>XS (40-42)| 78-86 (Грудь)| 58-66 см (Талия)| 86-94 см (Бёдра)<br><u>S (42-44)</u>| 82-90 (Грудь)&nbsp;| 62-70 см (Талия)| 90-98 см&nbsp;(Бёдра)<br><u>M (44-46)</u>|&nbsp;86-94 (Грудь)&nbsp;|66-74 см (Талия)| 94-102 см&nbsp;(Бёдра)<br><u>L&nbsp;(46-48)</u>| 90-98 (Грудь)&nbsp;| 70-78 см (Талия)| 98-104 см&nbsp;(Бёдра)<br><u>XL&nbsp;(48-50)</u>| 94-102 (Грудь)&nbsp;| 74-82 см (Талия)| 102-110 см&nbsp;(Бёдра)<br><u>ONESIZE (42-48)</u>&nbsp;| 78-98 (Грудь)&nbsp;| 62-78 см (Талия)| 82-104см&nbsp;(Бёдра)</p>",
      "care": "<p>- Не стирать<br>- Не отбеливать<br>- Температура утюга до 110 &deg;C<br>- Барабанная сушка запрещена<br>- Щадящая сухая чистка (химчистка)<br><br>Деликатный материал требует бережного обращения</p>"
    }
  ],
  "comments": [
    {
      "id": 1,
      "name": "Анна Смирнова",
      "image": "comment-1.jpg",
      "text": "Платье от этого бренда превзошло все ожидания! Качество ткани и пошива на высшем уровне. Теперь это мой любимый магазин для особых случаев."
    },
    {
      "id": 2,
      "name": "Екатерина Козлова",
      "image": "comment-2.jpg",
      "text": "Заказала кожаную куртку - получила настоящий шедевр! Идеальная посадка, все швы аккуратные. Доставили даже быстрее, чем обещали. Буду рекомендовать подругам!"
    },
    {
      "id": 3,
      "name": "Мария Волкова",
      "image": "comment-3.jpg",
      "text": "Обожаю, как в этом магазине сочетают смелые дизайнерские решения с комфортом. Кофта из новой коллекции - просто восторг! Носится каждый день и выглядит как новая."
    },
    {
      "id": 4,
      "name": "Ольга Новикова",
      "image": "comment-4.jpg",
      "text": "Первый раз заказала здесь брючный костюм - теперь понимаю, что такое настоящий дизайнерский крой. Сотрудники помогли с выбором размера - попали точно в яблочко!"
    }
  ],
  "news": [
    {
      "id": 1,
      "title": "Весенний SALE до 30%",
      "image": "news-1.png",
      "content": "<p>Уважаемые клиенты!</p><p>Праздники закончились, но не скидки! Весенний SALE до 30% на выборочный ассортимент из новой коллекции Весна-Лето 2025.</p><p>Весна - время обновлений: ждём вас за покупками!</p><p>Все подробности уточняйте у менеджеров магазина.</p>",
      "date": "14.05.2025"
    },
    {
      "id": 2,
      "title": "Праздничные скидки",
      "image": "news-2.png",
      "content": "<p>Уважаемые клиенты!</p><p>Поздравляем вас с праздниками и объявляем праздничную скидку до 30% на выборочный ассортимент из новой коллекции Весна-Лето 2025!</p><p>Акция действует с 7 по 12 мая 2025 года.</p><p>Хорошего вам настроения и отличного шопинга!</p><p>Все подробности уточняйте у менеджеров магазина.</p>",
      "date": "07.05.2025"
    },
    {
      "id": 3,
      "title": "Новая коллекция Sportalm уже в продаже",
      "image": "news-3.png",
      "content": "<p>Новая коллекция Весна-Лето' 2025 от&nbsp;Sportalm&nbsp;уже в продажe.</p><p>Порадуйте себя весенними новинками от любимого бренда!</p><p>Приятных вам покупок!</p>",
      "date": "14.04.2025"
    },
    {
      "id": 4,
      "title": "Новая коллекция DIEGO M уже в продаже",
      "image": "news-4.png",
      "content": "<p>Долгожданная новость от одного из самых любимых итальянских брендов! Новая коллекция Весна-Лето' 2025 от DIEGO M уже в продаже.</p><p>Торопитесь сделать ваш заказ пока в наличии есть все размеры!</p><p>Приятного вам шопинга!</p><p>Все подробности - у менеджеров магазина.</p>",
      "date": "28.03.2025"
    }
  ]
}
